<?xml version="1.0" encoding="UTF-8" standalone="yes"?><sst xmlns="http://schemas.openxmlformats.org/spreadsheetml/2006/main" count="39" uniqueCount="27"><si><t>CustomerRefNo</t></si><si><t>BoqNo</t></si><si><t>DESCRIPTION</t></si><si><t>IMAGE</t></si><si><t>UNIT</t></si><si><t>Quantity</t></si><si><t>RATE</t></si><si><t>AMOUNT</t></si><si><t>A</t></si><si><t>BUILDING</t></si><si><t>A.1</t></si><si><t>FLOOR</t></si><si><t>A.1.1</t></si><si><t>OFFICE 1</t></si><si><t>A1.1:1</t></si><si><t>L-SHAPE DESK
SIZE: 220</t></si><si><t>Nos.</t></si><si><t>A.1.2</t></si><si><t>ADMIN OFFICE 1 AND 2</t></si><si><t>A.1.2:1</t></si><si><t>DESK
SIZE: 210*90*75*160*40</t></si><si><t>A.1.3</t></si><si><t>ENGINEER &amp; TECHNICIAN WIND/ SUPERVISOR &amp; ADF INSPECTOR WIND / ENGINEER 1 2 END</t></si><si><t>A.1.3:1</t></si><si><t>TYPE 1 WORKSTATION FOR 1 PERSON 
SIZE: 230*170 EACH</t></si><si><t>A.1.3:2</t></si><si><t>L-SHAPE DESK
SIZE: 200</t></si></sst>